{
  "users": [
    {
      "email": "fabio@gmail.com",
      "password": "$2a$10$c6HIM68hAL0Cxy03NmpZ5.yW7C41kLgysJbmMNvhVICvM914oW7Pu",
      "name": "Fabio Yamashita",
      "isSeller": true,
      "id": 1
    },
    {
      "email": "teste@gmail.com",
      "password": "$2a$10$BGHK69.cRrQ9BKEpln4iwupvk4bH6paDIE099RCvjnMrhxzlSW1Sq",
      "name": "teste",
      "isSeller": true,
      "id": 2
    },
    {
      "email": "admin@admin.com",
      "password": "$2a$10$cTnG5vbDJPMZBTP2FOdOjO65OE4MesbT2MQyiK.9mcxjg1qypsf7O",
      "name": "admin",
      "isSeller": true,
      "id": 3
    }
  ],
  "dogs": [
    {
      "name": "Nina the Samoyed",
      "breed": "Samoyed",
      "genre": "Female",
      "price": 150.18,
      "availableQuantity": 2,
      "description": "Description Teste",
      "dateOfBirth": "2023-01-01",
      "weight": 35,
      "height": 12,
      "width": 5,
      "pictureUrl": "https://images.unsplash.com/photo-1625334955193-c7c208aba883?ixlib=rb-4.0.3&ixid=MnwxMjA3fDB8MHxwaG90by1wYWdlfHx8fGVufDB8fHx8&auto=format&fit=crop&w=735&q=80",
      "sellerId": 1,
      "id": 1
    },
    {
      "availableQuantity": 1,
      "name": "John",
      "breed": "Airedale Terrier",
      "genre": "Male",
      "price": 147,
      "description": "Test",
      "dateOfBirth": "2023-01-03",
      "weight": 15,
      "height": 14,
      "width": 15,
      "pictureUrl": "https://images.unsplash.com/photo-1558368315-d44d7462073e?ixlib=rb-4.0.3&ixid=MnwxMjA3fDB8MHxwaG90by1wYWdlfHx8fGVufDB8fHx8&auto=format&fit=crop&w=1165&q=80",
      "sellerId": 1,
      "id": 2
    },
    {
      "availableQuantity": 0,
      "name": "Maria",
      "breed": "Afghan Hound",
      "genre": "Female",
      "price": 142,
      "description": "Teste",
      "dateOfBirth": "2023-01-19",
      "weight": 14,
      "height": 14,
      "width": 10,
      "pictureUrl": "https://images.unsplash.com/photo-1561037404-61cd46aa615b?ixlib=rb-4.0.3&ixid=MnwxMjA3fDB8MHxwaG90by1wYWdlfHx8fGVufDB8fHx8&auto=format&fit=crop&w=1170&q=80",
      "sellerId": 1,
      "id": 3
    },
    {
      "availableQuantity": 2,
      "name": "Seller 2 Dog",
      "breed": "Australian Cattle Dog",
      "genre": "Male",
      "price": 125,
      "description": "teste",
      "dateOfBirth": "2023-01-21",
      "weight": 14,
      "height": 15,
      "width": 14,
      "pictureUrl": "https://images.unsplash.com/photo-1568640347023-a616a30bc3bd?ixlib=rb-4.0.3&ixid=MnwxMjA3fDB8MHxwaG90by1wYWdlfHx8fGVufDB8fHx8&auto=format&fit=crop&w=1173&q=80",
      "sellerId": 2,
      "id": 4
    },
    {
      "availableQuantity": 1,
      "name": "Admin dog",
      "breed": "Others",
      "genre": "Male",
      "price": 5000,
      "description": "Admin dog",
      "dateOfBirth": "2023-01-05",
      "weight": 50,
      "height": 50,
      "width": 50,
      "pictureUrl": "https://images.unsplash.com/photo-1535930749574-1399327ce78f?ixlib=rb-4.0.3&ixid=MnwxMjA3fDB8MHxwaG90by1wYWdlfHx8fGVufDB8fHx8&auto=format&fit=crop&w=736&q=80",
      "sellerId": 3,
      "id": 5
    }
  ],
  "carts": [
    {
      "id": 1,
      "userId": 1,
      "summary": 142,
      "discount": 0,
      "total": 142,
      "dogs": [
        {
          "dogId": 3,
          "quantity": 1
        }
      ]
    },
    {
      "id": 2,
      "userId": 2,
      "summary": 0,
      "discount": 0,
      "total": 0,
      "dogs": []
    },
    {
      "userId": 3,
      "summary": 0,
      "discount": 0,
      "total": 0,
      "dogs": [],
      "id": 3
    }
  ],
  "purchases": [
    {
      "date": "2023-01-21",
      "userId": 1,
      "summary": 425.36,
      "discount": 0,
      "total": 425.36,
      "dogs": [
        {
          "dogId": 1,
          "quantity": 2
        },
        {
          "dogId": 4,
          "quantity": 1
        }
      ],
      "id": 1
    },
    {
      "date": "2023-01-21",
      "userId": 1,
      "summary": 142,
      "discount": 0,
      "total": 142,
      "dogs": [
        {
          "dogId": 3,
          "quantity": 1
        }
      ],
      "id": 2
    },
    {
      "date": "2023-01-21",
      "userId": 2,
      "summary": 422.18,
      "discount": 0,
      "total": 422.18,
      "dogs": [
        {
          "dogId": 4,
          "quantity": 1
        },
        {
          "dogId": 1,
          "quantity": 1
        },
        {
          "dogId": 2,
          "quantity": 1
        }
      ],
      "id": 3
    }
  ]
}
